fieldview/__init__.py
fieldview/core/__init__.py
fieldview/core/data_container.py
fieldview/layers/__init__.py
fieldview/layers/data_layer.py
fieldview/layers/heatmap_layer.py
fieldview/layers/layer.py
fieldview/layers/pin_layer.py
fieldview/layers/svg_layer.py
fieldview/layers/text_layer.py
fieldview/rendering/__init__.py
fieldview/rendering/colormaps.py
fieldview/resources/fonts/JetBrainsMono-Regular.ttf
fieldview/ui/__init__.py
fieldview/ui/color_range_widget.py
fieldview/ui/data_table.py
fieldview/ui/field_view.py
fieldview/utils/grid_manager.py
fieldview/utils/interpolation.py
fieldview/utils/qt_compat.py
fieldview-0.3.1.dist-info/METADATA
fieldview-0.3.1.dist-info/WHEEL
fieldview-0.3.1.dist-info/RECORD
