Metadata-Version: 2.4
Name: fieldview
Version: 0.3.1
Summary: Python + Qt based 2D data visualization solution for irregular data points
Author-email: FieldView Team <dev@fieldview.org>
Requires-Python: >=3.10
Requires-Dist: numpy>=1.24.1
Requires-Dist: qtpy>=2.4.0
Requires-Dist: scipy>=1.10.0
Provides-Extra: pyqt5
Requires-Dist: pyqt5>=5.15.0; extra == 'pyqt5'
Provides-Extra: pyqt6
Requires-Dist: pyqt6>=6.6.0; extra == 'pyqt6'
Provides-Extra: pyside6
Requires-Dist: pyside6>=6.6.0; extra == 'pyside6'
